[
  {
    "id": "1",
    "subject": "Webbutveckling",
    "code": "DT057G",
    "name": "Webbutveckling I",
    "progression": "A",
    "semester": "HT20",
    "syllabus": "http://www.miun.se/utbildning/kurser/sok-kursplan/kursplan?kursplanid=15472"
  },
  {
    "id": "2",
    "subject": "Webbutveckling",
    "code": "DT093G",
    "name": "Webbutveckling II",
    "progression": "B",
    "semester": "VT21",
    "syllabus": "http://www.miun.se/utbildning/kurser/sok-kursplan/kursplan?kursplanid=15474"
  },
  {
    "id": "3",
    "subject": "Webbutveckling",
    "code": "DT003G",
    "name": "Databaser",
    "progression": "B",
    "semester": "VT21",
    "syllabus": "https://www.miun.se/utbildning/kursplaner-och-utbildningsplaner/Sok-kursplan/kursplan/?kursplanid=21595"
  },
  {
    "id": "4",
    "subject": "User friendly",
    "code": "DT068G",
    "name": "Webbanvändbarhet",
    "progression": "B",
    "semester": "HT20",
    "syllabus": "https://www.miun.se/utbildning/kursplaner-och-utbildningsplaner/Sok-kursplan/kursplan/?kursplanid=30563"
  },
  {
    "id": "5",
    "subject": "Webbutveckling",
    "code": "DT191G",
    "name": "Webbutveckling med .NET",
    "progression": "B",
    "semester": "VT22",
    "syllabus": "https://www.miun.se/utbildning/kursplaner-och-utbildningsplaner/Sok-kursplan/kursplan/?kursplanid=25557"
  },
  {
    "id": "6",
    "subject": "Webbutveckling",
    "code": "DT084G",
    "name": "Introduktion till programmering i JavaScript",
    "progression": "A",
    "semester": "HT20",
    "syllabus": "https://www.miun.se/utbildning/kursplaner-och-utbildningsplaner/Sok-kursplan/kursplan/?kursplanid=30554"
  },
  {
    "id": "7",
    "subject": "Webbutveckling",
    "code": "DT102G",
    "name": "ASP.NET med C#",
    "progression": "B",
    "semester": "HT21",
    "syllabus": "https://www.miun.se/utbildning/kursplaner-och-utbildningsplaner/Sok-kursplan/kursplan/?kursplanid=22325"
  },
  {
    "id": "8",
    "subject": "Webbutveckling",
    "code": "DT152G",
    "name": "Webbdesign för CMS",
    "progression": "B",
    "semester": "VT21",
    "syllabus": "https://www.miun.se/utbildning/kursplaner-och-utbildningsplaner/Sok-kursplan/kursplan/?kursplanid=22324"
  },
  {
    "id": "9",
    "subject": "Webbutveckling",
    "code": "DT162G",
    "name": "Javascriptbaserad webbutveckling",
    "progression": "B",
    "semester": "HT21",
    "syllabus": "https://www.miun.se/utbildning/kursplaner-och-utbildningsplaner/Sok-kursplan/kursplan/?kursplanid=24366"
  },
  {
    "id": "10",
    "subject": "User friendly",
    "code": "DT163G",
    "name": "Digital bildbehandling för webb",
    "progression": "A",
    "semester": "HT20",
    "syllabus": "https://www.miun.se/utbildning/kursplaner-och-utbildningsplaner/Sok-kursplan/kursplan/?kursplanid=24403"
  },
  {
    "id": "11",
    "subject": "Webbutveckling",
    "code": "DT173G",
    "name": "Webbutveckling III",
    "progression": "B",
    "semester": "VT21",
    "syllabus": "https://www.miun.se/utbildning/kursplaner-och-utbildningsplaner/Sok-kursplan/kursplan/?kursplanid=22706"
  },
  {
    "id": "12",
    "subject": "User friendly",
    "code": "GD008G",
    "name": "Typografi och form för webb",
    "progression": "A",
    "semester": "HT21",
    "syllabus": "https://www.miun.se/utbildning/kursplaner-och-utbildningsplaner/Sok-kursplan/kursplan/?kursplanid=24399"
  }
]